calc/__init__.py
calc/__main__.py
calc/app.py
calc/window/__init__.py
calc/window/design/__init__.py
calc/window/design/main_window.py
calc/window/design/main_window.ui
calc/window/widgets/__init__.py
calc/window/widgets/digit_button.py
calc/window/widgets/operator_button.py
calc/window/window.py
calc_with_bugs-0.1.0.dist-info/METADATA
calc_with_bugs-0.1.0.dist-info/WHEEL
calc_with_bugs-0.1.0.dist-info/RECORD
