Metadata-Version: 2.1
Name: calc-with-bugs
Version: 0.1.0
Summary: 
Author: Artem Burenin
Author-email: burenin@mindbox.cloud
Requires-Python: >=3.8,<4.0
Classifier: Programming Language :: Python :: 3
Classifier: Programming Language :: Python :: 3.8
Classifier: Programming Language :: Python :: 3.9
Classifier: Programming Language :: Python :: 3.10
Classifier: Programming Language :: Python :: 3.11
Classifier: Programming Language :: Python :: 3.12
Requires-Dist: pyqt6 (>=6.4.2,<7.0.0)
